MANIFEST.in
README.rst
setup.py
zcbot_url_parser/__init__.py
zcbot_url_parser/constant.py
zcbot_url_parser/file_name_config.py
zcbot_url_parser/image_thumb_config.py
zcbot_url_parser/parser.py
zcbot_url_parser/rule.py
zcbot_url_parser/spider.py
zcbot_url_parser/utils.py
zcbot_url_parser.egg-info/PKG-INFO
zcbot_url_parser.egg-info/SOURCES.txt
zcbot_url_parser.egg-info/dependency_links.txt
zcbot_url_parser.egg-info/not-zip-safe
zcbot_url_parser.egg-info/requires.txt
zcbot_url_parser.egg-info/top_level.txt