Metadata-Version: 2.1
Name: zcbot-url-parser
Version: 1.0.14
Summary: zcbot url parser for zsodata
Home-page: http://www.zsodata.com
Author: zsodata
Author-email: team@zso.io
License: BSD License
Platform: all
Requires-Python: >=3.7
